{
  "request": {
    "method": "GET",
    "path": "/brave_eagle/tasks"
  },
  "response": {
    "status": 200,
    "body": {
      "tasks": [
        {
          "id": "6da302ea-ac15-444f-bf4f-b37960ba8c9e",
          "title": "Write documentation",
          "description": "Complete the API reference guide",
          "status": "pending",
          "priority": "high",
          "dueDate": null,
          "archived": false,
          "createdAt": "2025-12-18T13:29:03.712Z",
          "updatedAt": "2025-12-18T13:29:03.712Z"
        },
        {
          "id": "b3858888-2fb0-4350-86a8-df13975aad90",
          "title": "Review pull request",
          "description": null,
          "status": "completed",
          "priority": "medium",
          "dueDate": null,
          "archived": false,
          "createdAt": "2025-12-18T13:29:03.714Z",
          "updatedAt": "2025-12-18T13:29:03.714Z"
        }
      ],
      "pagination": {
        "current": 1,
        "next": null,
        "prev": null,
        "total": 1,
        "items": 2
      }
    }
  }
}