{
  "request": {
    "method": "POST",
    "path": "/mighty_wolf/vehicles",
    "body": {
      "vehicle": {
        "type": "car",
        "brand": "Volvo",
        "model": "EX30",
        "year": 2024,
        "color": "red"
      }
    }
  },
  "response": {
    "status": 201,
    "body": {
      "vehicle": {
        "type": "car",
        "id": "7015512c-69be-4a5d-9168-d862a33d2132",
        "brand": "Volvo",
        "model": "EX30",
        "year": 2024,
        "color": "red",
        "doors": null
      }
    }
  }
}