{
  "request": {
    "method": "GET",
    "path": "/mighty-wolf/vehicles"
  },
  "response": {
    "status": 200,
    "body": {
      "vehicles": [
        {
          "kind": "car",
          "id": "bab608b2-e622-42d3-96ed-38854661f74c",
          "brand": "Tesla",
          "model": "Model 3",
          "year": null,
          "color": null,
          "doors": null
        },
        {
          "kind": "motorcycle",
          "id": "f328c339-8b2d-43de-9f57-91be505af4ff",
          "brand": "Harley-Davidson",
          "model": "Street Glide",
          "year": null,
          "color": null,
          "engine_cc": null
        },
        {
          "kind": "truck",
          "id": "ccf0cb33-9aeb-466a-baf0-dd4a394d2279",
          "brand": "Ford",
          "model": "F-150",
          "year": null,
          "color": null,
          "payload_capacity": null
        }
      ],
      "pagination": {
        "current": 1,
        "next": null,
        "prev": null,
        "total": 1,
        "items": 3
      }
    }
  }
}