{
  "request": {
    "method": "GET",
    "path": "/mighty_wolf/vehicles"
  },
  "response": {
    "status": 200,
    "body": {
      "vehicles": [
        {
          "type": "car",
          "id": "8f56fbba-c86e-4a2e-8716-6829339d9d58",
          "brand": "Volvo",
          "model": "EX30",
          "year": null,
          "color": null,
          "doors": null
        },
        {
          "type": "motorcycle",
          "id": "5584c7fd-8eb8-444f-89ab-1cfc5dc331a7",
          "brand": "Harley-Davidson",
          "model": "Street Glide",
          "year": null,
          "color": null,
          "engineCc": null
        },
        {
          "type": "truck",
          "id": "bac70bfd-4630-460f-94d7-929e337b68cd",
          "brand": "Ford",
          "model": "F-150",
          "year": null,
          "color": null,
          "payloadCapacity": null
        }
      ],
      "pagination": {
        "current": 1,
        "next": null,
        "prev": null,
        "total": 1,
        "items": 3
      }
    }
  }
}