{
  "request": {
    "method": "POST",
    "path": "/happy_zebra/users",
    "body": {
      "user": {
        "email": "deep@example.com",
        "username": "deepuser",
        "posts": [
          {
            "title": "My First Post",
            "comments": [
              {
                "body": "Great post!",
                "author": "Jane"
              },
              {
                "body": "Thanks for sharing",
                "author": "Bob"
              }
            ]
          }
        ]
      }
    }
  },
  "response": {
    "status": 201,
    "body": {
      "user": {
        "id": "b4d8ccd0-7107-4940-b5b3-fd8b688a23f9",
        "createdAt": "2025-12-18T13:29:04.403Z",
        "updatedAt": "2025-12-18T13:29:04.403Z",
        "email": "deep@example.com",
        "username": "deepuser",
        "profile": null,
        "posts": [
          {
            "id": "6c16cc1a-652c-40c2-8be8-22cbd6638ea5",
            "title": "My First Post",
            "comments": [
              {
                "id": "b8fd5e2b-6343-4b2f-bfbc-498026adc188",
                "body": "Great post!",
                "author": "Jane"
              },
              {
                "id": "aef53ce7-48e8-4f72-90f2-c1140432a957",
                "body": "Thanks for sharing",
                "author": "Bob"
              }
            ]
          }
        ]
      }
    }
  }
}