{
  "base_path": "/eager_lion",
  "enums": {
    "invoice_status": {
      "deprecated": false,
      "description": null,
      "example": null,
      "values": [
        "draft",
        "sent",
        "paid"
      ]
    },
    "layer": {
      "deprecated": false,
      "description": null,
      "example": null,
      "values": [
        "http",
        "contract",
        "domain"
      ]
    },
    "sort_direction": {
      "deprecated": false,
      "description": null,
      "example": null,
      "values": [
        "asc",
        "desc"
      ]
    }
  },
  "error_codes": {
    "unprocessable_entity": {
      "description": "Unprocessable Entity",
      "status": 422
    }
  },
  "info": null,
  "resources": {
    "invoices": {
      "actions": {
        "index": {
          "deprecated": false,
          "description": null,
          "method": "get",
          "operation_id": null,
          "path": "/invoices",
          "raises": [],
          "request": {
            "body": {},
            "query": {
              "filter": {
                "default": null,
                "deprecated": false,
                "description": null,
                "example": null,
                "nullable": false,
                "optional": true,
                "type": "union",
                "discriminator": null,
                "variants": [
                  {
                    "default": null,
                    "deprecated": false,
                    "description": null,
                    "example": null,
                    "nullable": false,
                    "optional": false,
                    "type": "reference",
                    "reference": "invoice_filter"
                  },
                  {
                    "default": null,
                    "deprecated": false,
                    "description": null,
                    "example": null,
                    "nullable": false,
                    "optional": false,
                    "type": "array",
                    "max": null,
                    "min": null,
                    "of": {
                      "default": null,
                      "deprecated": null,
                      "description": null,
                      "example": null,
                      "nullable": null,
                      "optional": null,
                      "type": "reference",
                      "reference": "invoice_filter"
                    },
                    "shape": {}
                  }
                ]
              },
              "page": {
                "default": null,
                "deprecated": false,
                "description": null,
                "example": null,
                "nullable": false,
                "optional": true,
                "type": "reference",
                "reference": "invoice_page"
              },
              "sort": {
                "default": null,
                "deprecated": false,
                "description": null,
                "example": null,
                "nullable": false,
                "optional": true,
                "type": "union",
                "discriminator": null,
                "variants": [
                  {
                    "default": null,
                    "deprecated": false,
                    "description": null,
                    "example": null,
                    "nullable": false,
                    "optional": false,
                    "type": "reference",
                    "reference": "invoice_sort"
                  },
                  {
                    "default": null,
                    "deprecated": false,
                    "description": null,
                    "example": null,
                    "nullable": false,
                    "optional": false,
                    "type": "array",
                    "max": null,
                    "min": null,
                    "of": {
                      "default": null,
                      "deprecated": null,
                      "description": null,
                      "example": null,
                      "nullable": null,
                      "optional": null,
                      "type": "reference",
                      "reference": "invoice_sort"
                    },
                    "shape": {}
                  }
                ]
              }
            }
          },
          "response": {
            "body": {
              "default": null,
              "deprecated": null,
              "description": null,
              "example": null,
              "nullable": null,
              "optional": null,
              "type": "union",
              "discriminator": null,
              "variants": [
                {
                  "default": null,
                  "deprecated": null,
                  "description": null,
                  "example": null,
                  "nullable": null,
                  "optional": null,
                  "type": "reference",
                  "reference": "invoice_index_success_response_body"
                },
                {
                  "default": null,
                  "deprecated": null,
                  "description": null,
                  "example": null,
                  "nullable": null,
                  "optional": null,
                  "type": "reference",
                  "reference": "error_response_body"
                }
              ]
            },
            "no_content": false
          },
          "summary": null,
          "tags": []
        },
        "show": {
          "deprecated": false,
          "description": null,
          "method": "get",
          "operation_id": null,
          "path": "/invoices/:id",
          "raises": [],
          "request": {
            "body": {},
            "query": {}
          },
          "response": {
            "body": {
              "default": null,
              "deprecated": null,
              "description": null,
              "example": null,
              "nullable": null,
              "optional": null,
              "type": "union",
              "discriminator": null,
              "variants": [
                {
                  "default": null,
                  "deprecated": null,
                  "description": null,
                  "example": null,
                  "nullable": null,
                  "optional": null,
                  "type": "reference",
                  "reference": "invoice_show_success_response_body"
                },
                {
                  "default": null,
                  "deprecated": null,
                  "description": null,
                  "example": null,
                  "nullable": null,
                  "optional": null,
                  "type": "reference",
                  "reference": "error_response_body"
                }
              ]
            },
            "no_content": false
          },
          "summary": null,
          "tags": []
        },
        "create": {
          "deprecated": false,
          "description": null,
          "method": "post",
          "operation_id": null,
          "path": "/invoices",
          "raises": [
            "unprocessable_entity"
          ],
          "request": {
            "body": {
              "invoice": {
                "default": null,
                "deprecated": false,
                "description": null,
                "example": null,
                "nullable": false,
                "optional": false,
                "type": "reference",
                "reference": "invoice_create_payload"
              }
            },
            "query": {}
          },
          "response": {
            "body": {
              "default": null,
              "deprecated": null,
              "description": null,
              "example": null,
              "nullable": null,
              "optional": null,
              "type": "union",
              "discriminator": null,
              "variants": [
                {
                  "default": null,
                  "deprecated": null,
                  "description": null,
                  "example": null,
                  "nullable": null,
                  "optional": null,
                  "type": "reference",
                  "reference": "invoice_create_success_response_body"
                },
                {
                  "default": null,
                  "deprecated": null,
                  "description": null,
                  "example": null,
                  "nullable": null,
                  "optional": null,
                  "type": "reference",
                  "reference": "error_response_body"
                }
              ]
            },
            "no_content": false
          },
          "summary": null,
          "tags": []
        },
        "update": {
          "deprecated": false,
          "description": null,
          "method": "patch",
          "operation_id": null,
          "path": "/invoices/:id",
          "raises": [
            "unprocessable_entity"
          ],
          "request": {
            "body": {
              "invoice": {
                "default": null,
                "deprecated": false,
                "description": null,
                "example": null,
                "nullable": false,
                "optional": false,
                "type": "reference",
                "reference": "invoice_update_payload"
              }
            },
            "query": {}
          },
          "response": {
            "body": {
              "default": null,
              "deprecated": null,
              "description": null,
              "example": null,
              "nullable": null,
              "optional": null,
              "type": "union",
              "discriminator": null,
              "variants": [
                {
                  "default": null,
                  "deprecated": null,
                  "description": null,
                  "example": null,
                  "nullable": null,
                  "optional": null,
                  "type": "reference",
                  "reference": "invoice_update_success_response_body"
                },
                {
                  "default": null,
                  "deprecated": null,
                  "description": null,
                  "example": null,
                  "nullable": null,
                  "optional": null,
                  "type": "reference",
                  "reference": "error_response_body"
                }
              ]
            },
            "no_content": false
          },
          "summary": null,
          "tags": []
        },
        "destroy": {
          "deprecated": false,
          "description": null,
          "method": "delete",
          "operation_id": null,
          "path": "/invoices/:id",
          "raises": [],
          "request": {
            "body": {},
            "query": {}
          },
          "response": {
            "body": {
              "default": null,
              "deprecated": null,
              "description": null,
              "example": null,
              "nullable": null,
              "optional": null,
              "type": null
            },
            "no_content": true
          },
          "summary": null,
          "tags": []
        },
        "archive": {
          "deprecated": false,
          "description": null,
          "method": "patch",
          "operation_id": null,
          "path": "/invoices/:id/archive",
          "raises": [
            "unprocessable_entity"
          ],
          "request": {
            "body": {},
            "query": {}
          },
          "response": {
            "body": {
              "default": null,
              "deprecated": null,
              "description": null,
              "example": null,
              "nullable": null,
              "optional": null,
              "type": "union",
              "discriminator": null,
              "variants": [
                {
                  "default": null,
                  "deprecated": null,
                  "description": null,
                  "example": null,
                  "nullable": null,
                  "optional": null,
                  "type": "reference",
                  "reference": "invoice_archive_success_response_body"
                },
                {
                  "default": null,
                  "deprecated": null,
                  "description": null,
                  "example": null,
                  "nullable": null,
                  "optional": null,
                  "type": "reference",
                  "reference": "error_response_body"
                }
              ]
            },
            "no_content": false
          },
          "summary": null,
          "tags": []
        }
      },
      "identifier": "invoices",
      "parent_identifiers": [],
      "path": "invoices",
      "resources": {}
    }
  },
  "types": {
    "customer": {
      "deprecated": false,
      "description": null,
      "discriminator": null,
      "example": null,
      "extends": [],
      "shape": {
        "id": {
          "default": null,
          "deprecated": false,
          "description": null,
          "example": null,
          "nullable": false,
          "optional": false,
          "type": "string",
          "format": null,
          "max": null,
          "min": null
        },
        "name": {
          "default": null,
          "deprecated": false,
          "description": null,
          "example": null,
          "nullable": false,
          "optional": false,
          "type": "string",
          "format": null,
          "max": null,
          "min": null
        }
      },
      "type": "object",
      "variants": []
    },
    "customer_create_payload": {
      "deprecated": false,
      "description": null,
      "discriminator": null,
      "example": null,
      "extends": [],
      "shape": {},
      "type": "object",
      "variants": []
    },
    "customer_update_payload": {
      "deprecated": false,
      "description": null,
      "discriminator": null,
      "example": null,
      "extends": [],
      "shape": {},
      "type": "object",
      "variants": []
    },
    "error": {
      "deprecated": false,
      "description": null,
      "discriminator": null,
      "example": null,
      "extends": [],
      "shape": {
        "issues": {
          "default": null,
          "deprecated": false,
          "description": null,
          "example": null,
          "nullable": false,
          "optional": false,
          "type": "array",
          "max": null,
          "min": null,
          "of": {
            "default": null,
            "deprecated": null,
            "description": null,
            "example": null,
            "nullable": null,
            "optional": null,
            "type": "reference",
            "reference": "issue"
          },
          "shape": {}
        },
        "layer": {
          "default": null,
          "deprecated": false,
          "description": null,
          "example": null,
          "nullable": false,
          "optional": false,
          "type": "reference",
          "reference": "layer"
        }
      },
      "type": "object",
      "variants": []
    },
    "error_response_body": {
      "deprecated": false,
      "description": null,
      "discriminator": null,
      "example": null,
      "extends": [
        "error"
      ],
      "shape": {},
      "type": "object",
      "variants": []
    },
    "invoice": {
      "deprecated": false,
      "description": null,
      "discriminator": null,
      "example": null,
      "extends": [],
      "shape": {
        "created_at": {
          "default": null,
          "deprecated": false,
          "description": null,
          "example": null,
          "nullable": false,
          "optional": false,
          "type": "datetime"
        },
        "customer": {
          "default": null,
          "deprecated": false,
          "description": null,
          "example": null,
          "nullable": false,
          "optional": false,
          "type": "reference",
          "reference": "customer"
        },
        "customer_id": {
          "default": null,
          "deprecated": false,
          "description": null,
          "example": null,
          "nullable": false,
          "optional": false,
          "type": "string",
          "format": null,
          "max": null,
          "min": null
        },
        "id": {
          "default": null,
          "deprecated": false,
          "description": null,
          "example": null,
          "nullable": false,
          "optional": false,
          "type": "string",
          "format": null,
          "max": null,
          "min": null
        },
        "issued_on": {
          "default": null,
          "deprecated": false,
          "description": null,
          "example": null,
          "nullable": true,
          "optional": false,
          "type": "date"
        },
        "lines": {
          "default": null,
          "deprecated": false,
          "description": null,
          "example": null,
          "nullable": false,
          "optional": false,
          "type": "array",
          "max": null,
          "min": null,
          "of": {
            "default": null,
            "deprecated": null,
            "description": null,
            "example": null,
            "nullable": null,
            "optional": null,
            "type": "reference",
            "reference": "line"
          },
          "shape": {}
        },
        "notes": {
          "default": null,
          "deprecated": false,
          "description": null,
          "example": null,
          "nullable": true,
          "optional": false,
          "type": "string",
          "format": null,
          "max": null,
          "min": null
        },
        "number": {
          "default": null,
          "deprecated": false,
          "description": null,
          "example": null,
          "nullable": false,
          "optional": false,
          "type": "string",
          "format": null,
          "max": null,
          "min": null
        },
        "status": {
          "default": null,
          "deprecated": false,
          "description": null,
          "example": null,
          "nullable": true,
          "optional": false,
          "type": "string",
          "enum": "invoice_status",
          "format": null,
          "max": null,
          "min": null
        },
        "updated_at": {
          "default": null,
          "deprecated": false,
          "description": null,
          "example": null,
          "nullable": false,
          "optional": false,
          "type": "datetime"
        }
      },
      "type": "object",
      "variants": []
    },
    "invoice_archive_success_response_body": {
      "deprecated": false,
      "description": null,
      "discriminator": null,
      "example": null,
      "extends": [],
      "shape": {
        "invoice": {
          "default": null,
          "deprecated": false,
          "description": null,
          "example": null,
          "nullable": false,
          "optional": false,
          "type": "reference",
          "reference": "invoice"
        },
        "meta": {
          "default": null,
          "deprecated": false,
          "description": null,
          "example": null,
          "nullable": false,
          "optional": true,
          "type": "object",
          "partial": false,
          "shape": {}
        }
      },
      "type": "object",
      "variants": []
    },
    "invoice_create_payload": {
      "deprecated": false,
      "description": null,
      "discriminator": null,
      "example": null,
      "extends": [],
      "shape": {
        "customer_id": {
          "default": null,
          "deprecated": false,
          "description": null,
          "example": null,
          "nullable": false,
          "optional": false,
          "type": "string",
          "format": null,
          "max": null,
          "min": null
        },
        "issued_on": {
          "default": null,
          "deprecated": false,
          "description": null,
          "example": null,
          "nullable": true,
          "optional": true,
          "type": "date"
        },
        "lines": {
          "default": null,
          "deprecated": false,
          "description": null,
          "example": null,
          "nullable": false,
          "optional": true,
          "type": "array",
          "max": null,
          "min": null,
          "of": {
            "default": null,
            "deprecated": null,
            "description": null,
            "example": null,
            "nullable": null,
            "optional": null,
            "type": "reference",
            "reference": "line_nested_payload"
          },
          "shape": {}
        },
        "notes": {
          "default": null,
          "deprecated": false,
          "description": null,
          "example": null,
          "nullable": true,
          "optional": true,
          "type": "string",
          "format": null,
          "max": null,
          "min": null
        },
        "number": {
          "default": null,
          "deprecated": false,
          "description": null,
          "example": null,
          "nullable": false,
          "optional": false,
          "type": "string",
          "format": null,
          "max": null,
          "min": null
        }
      },
      "type": "object",
      "variants": []
    },
    "invoice_create_success_response_body": {
      "deprecated": false,
      "description": null,
      "discriminator": null,
      "example": null,
      "extends": [],
      "shape": {
        "invoice": {
          "default": null,
          "deprecated": false,
          "description": null,
          "example": null,
          "nullable": false,
          "optional": false,
          "type": "reference",
          "reference": "invoice"
        },
        "meta": {
          "default": null,
          "deprecated": false,
          "description": null,
          "example": null,
          "nullable": false,
          "optional": true,
          "type": "object",
          "partial": false,
          "shape": {}
        }
      },
      "type": "object",
      "variants": []
    },
    "invoice_filter": {
      "deprecated": false,
      "description": null,
      "discriminator": null,
      "example": null,
      "extends": [],
      "shape": {
        "AND": {
          "default": null,
          "deprecated": false,
          "description": null,
          "example": null,
          "nullable": false,
          "optional": true,
          "type": "array",
          "max": null,
          "min": null,
          "of": {
            "default": null,
            "deprecated": null,
            "description": null,
            "example": null,
            "nullable": null,
            "optional": null,
            "type": "reference",
            "reference": "invoice_filter"
          },
          "shape": {}
        },
        "NOT": {
          "default": null,
          "deprecated": false,
          "description": null,
          "example": null,
          "nullable": false,
          "optional": true,
          "type": "reference",
          "reference": "invoice_filter"
        },
        "OR": {
          "default": null,
          "deprecated": false,
          "description": null,
          "example": null,
          "nullable": false,
          "optional": true,
          "type": "array",
          "max": null,
          "min": null,
          "of": {
            "default": null,
            "deprecated": null,
            "description": null,
            "example": null,
            "nullable": null,
            "optional": null,
            "type": "reference",
            "reference": "invoice_filter"
          },
          "shape": {}
        },
        "number": {
          "default": null,
          "deprecated": false,
          "description": null,
          "example": null,
          "nullable": false,
          "optional": true,
          "type": "union",
          "discriminator": null,
          "variants": [
            {
              "default": null,
              "deprecated": false,
              "description": null,
              "example": null,
              "nullable": false,
              "optional": false,
              "type": "string",
              "format": null,
              "max": null,
              "min": null
            },
            {
              "default": null,
              "deprecated": false,
              "description": null,
              "example": null,
              "nullable": false,
              "optional": false,
              "type": "reference",
              "reference": "string_filter"
            }
          ]
        },
        "status": {
          "default": null,
          "deprecated": false,
          "description": null,
          "example": null,
          "nullable": false,
          "optional": true,
          "type": "reference",
          "reference": "invoice_status_filter"
        }
      },
      "type": "object",
      "variants": []
    },
    "invoice_index_success_response_body": {
      "deprecated": false,
      "description": null,
      "discriminator": null,
      "example": null,
      "extends": [],
      "shape": {
        "pagination": {
          "default": null,
          "deprecated": false,
          "description": null,
          "example": null,
          "nullable": false,
          "optional": false,
          "type": "reference",
          "reference": "offset_pagination"
        },
        "invoices": {
          "default": null,
          "deprecated": false,
          "description": null,
          "example": null,
          "nullable": false,
          "optional": false,
          "type": "array",
          "max": null,
          "min": null,
          "of": {
            "default": null,
            "deprecated": null,
            "description": null,
            "example": null,
            "nullable": null,
            "optional": null,
            "type": "reference",
            "reference": "invoice"
          },
          "shape": {}
        },
        "meta": {
          "default": null,
          "deprecated": false,
          "description": null,
          "example": null,
          "nullable": false,
          "optional": true,
          "type": "object",
          "partial": false,
          "shape": {}
        }
      },
      "type": "object",
      "variants": []
    },
    "invoice_page": {
      "deprecated": false,
      "description": null,
      "discriminator": null,
      "example": null,
      "extends": [],
      "shape": {
        "number": {
          "default": null,
          "deprecated": false,
          "description": null,
          "example": null,
          "nullable": false,
          "optional": true,
          "type": "integer",
          "format": null,
          "max": null,
          "min": 1
        },
        "size": {
          "default": null,
          "deprecated": false,
          "description": null,
          "example": null,
          "nullable": false,
          "optional": true,
          "type": "integer",
          "format": null,
          "max": 100,
          "min": 1
        }
      },
      "type": "object",
      "variants": []
    },
    "invoice_show_success_response_body": {
      "deprecated": false,
      "description": null,
      "discriminator": null,
      "example": null,
      "extends": [],
      "shape": {
        "invoice": {
          "default": null,
          "deprecated": false,
          "description": null,
          "example": null,
          "nullable": false,
          "optional": false,
          "type": "reference",
          "reference": "invoice"
        },
        "meta": {
          "default": null,
          "deprecated": false,
          "description": null,
          "example": null,
          "nullable": false,
          "optional": true,
          "type": "object",
          "partial": false,
          "shape": {}
        }
      },
      "type": "object",
      "variants": []
    },
    "invoice_sort": {
      "deprecated": false,
      "description": null,
      "discriminator": null,
      "example": null,
      "extends": [],
      "shape": {
        "created_at": {
          "default": null,
          "deprecated": false,
          "description": null,
          "example": null,
          "nullable": false,
          "optional": true,
          "type": "reference",
          "reference": "sort_direction"
        },
        "issued_on": {
          "default": null,
          "deprecated": false,
          "description": null,
          "example": null,
          "nullable": false,
          "optional": true,
          "type": "reference",
          "reference": "sort_direction"
        },
        "status": {
          "default": null,
          "deprecated": false,
          "description": null,
          "example": null,
          "nullable": false,
          "optional": true,
          "type": "reference",
          "reference": "sort_direction"
        },
        "updated_at": {
          "default": null,
          "deprecated": false,
          "description": null,
          "example": null,
          "nullable": false,
          "optional": true,
          "type": "reference",
          "reference": "sort_direction"
        }
      },
      "type": "object",
      "variants": []
    },
    "invoice_status_filter": {
      "deprecated": false,
      "description": null,
      "discriminator": null,
      "example": null,
      "extends": [],
      "shape": {},
      "type": "union",
      "variants": [
        {
          "default": null,
          "deprecated": false,
          "description": null,
          "example": null,
          "nullable": false,
          "optional": false,
          "type": "reference",
          "reference": "invoice_status"
        },
        {
          "default": null,
          "deprecated": false,
          "description": null,
          "example": null,
          "nullable": false,
          "optional": false,
          "type": "object",
          "partial": true,
          "shape": {
            "eq": {
              "default": null,
              "deprecated": false,
              "description": null,
              "example": null,
              "nullable": false,
              "optional": false,
              "type": "reference",
              "reference": "invoice_status"
            },
            "in": {
              "default": null,
              "deprecated": false,
              "description": null,
              "example": null,
              "nullable": false,
              "optional": false,
              "type": "array",
              "max": null,
              "min": null,
              "of": {
                "default": null,
                "deprecated": null,
                "description": null,
                "example": null,
                "nullable": null,
                "optional": null,
                "type": "reference",
                "reference": "invoice_status"
              },
              "shape": {}
            }
          }
        }
      ]
    },
    "invoice_update_payload": {
      "deprecated": false,
      "description": null,
      "discriminator": null,
      "example": null,
      "extends": [],
      "shape": {
        "customer_id": {
          "default": null,
          "deprecated": false,
          "description": null,
          "example": null,
          "nullable": false,
          "optional": true,
          "type": "string",
          "format": null,
          "max": null,
          "min": null
        },
        "issued_on": {
          "default": null,
          "deprecated": false,
          "description": null,
          "example": null,
          "nullable": true,
          "optional": true,
          "type": "date"
        },
        "lines": {
          "default": null,
          "deprecated": false,
          "description": null,
          "example": null,
          "nullable": false,
          "optional": true,
          "type": "array",
          "max": null,
          "min": null,
          "of": {
            "default": null,
            "deprecated": null,
            "description": null,
            "example": null,
            "nullable": null,
            "optional": null,
            "type": "reference",
            "reference": "line_nested_payload"
          },
          "shape": {}
        },
        "notes": {
          "default": null,
          "deprecated": false,
          "description": null,
          "example": null,
          "nullable": true,
          "optional": true,
          "type": "string",
          "format": null,
          "max": null,
          "min": null
        },
        "number": {
          "default": null,
          "deprecated": false,
          "description": null,
          "example": null,
          "nullable": false,
          "optional": true,
          "type": "string",
          "format": null,
          "max": null,
          "min": null
        }
      },
      "type": "object",
      "variants": []
    },
    "invoice_update_success_response_body": {
      "deprecated": false,
      "description": null,
      "discriminator": null,
      "example": null,
      "extends": [],
      "shape": {
        "invoice": {
          "default": null,
          "deprecated": false,
          "description": null,
          "example": null,
          "nullable": false,
          "optional": false,
          "type": "reference",
          "reference": "invoice"
        },
        "meta": {
          "default": null,
          "deprecated": false,
          "description": null,
          "example": null,
          "nullable": false,
          "optional": true,
          "type": "object",
          "partial": false,
          "shape": {}
        }
      },
      "type": "object",
      "variants": []
    },
    "issue": {
      "deprecated": false,
      "description": null,
      "discriminator": null,
      "example": null,
      "extends": [],
      "shape": {
        "code": {
          "default": null,
          "deprecated": false,
          "description": null,
          "example": null,
          "nullable": false,
          "optional": false,
          "type": "string",
          "format": null,
          "max": null,
          "min": null
        },
        "detail": {
          "default": null,
          "deprecated": false,
          "description": null,
          "example": null,
          "nullable": false,
          "optional": false,
          "type": "string",
          "format": null,
          "max": null,
          "min": null
        },
        "meta": {
          "default": null,
          "deprecated": false,
          "description": null,
          "example": null,
          "nullable": false,
          "optional": false,
          "type": "object",
          "partial": false,
          "shape": {}
        },
        "path": {
          "default": null,
          "deprecated": false,
          "description": null,
          "example": null,
          "nullable": false,
          "optional": false,
          "type": "array",
          "max": null,
          "min": null,
          "of": {
            "default": null,
            "deprecated": null,
            "description": null,
            "example": null,
            "nullable": null,
            "optional": null,
            "type": "string",
            "format": null,
            "max": null,
            "min": null
          },
          "shape": {}
        },
        "pointer": {
          "default": null,
          "deprecated": false,
          "description": null,
          "example": null,
          "nullable": false,
          "optional": false,
          "type": "string",
          "format": null,
          "max": null,
          "min": null
        }
      },
      "type": "object",
      "variants": []
    },
    "line": {
      "deprecated": false,
      "description": null,
      "discriminator": null,
      "example": null,
      "extends": [],
      "shape": {
        "description": {
          "default": null,
          "deprecated": false,
          "description": null,
          "example": null,
          "nullable": true,
          "optional": false,
          "type": "string",
          "format": null,
          "max": null,
          "min": null
        },
        "id": {
          "default": null,
          "deprecated": false,
          "description": null,
          "example": null,
          "nullable": false,
          "optional": false,
          "type": "string",
          "format": null,
          "max": null,
          "min": null
        },
        "price": {
          "default": null,
          "deprecated": false,
          "description": null,
          "example": null,
          "nullable": true,
          "optional": false,
          "type": "decimal",
          "max": null,
          "min": null
        },
        "quantity": {
          "default": null,
          "deprecated": false,
          "description": null,
          "example": null,
          "nullable": true,
          "optional": false,
          "type": "integer",
          "format": null,
          "max": null,
          "min": null
        }
      },
      "type": "object",
      "variants": []
    },
    "line_create_payload": {
      "deprecated": false,
      "description": null,
      "discriminator": null,
      "example": null,
      "extends": [],
      "shape": {
        "description": {
          "default": null,
          "deprecated": false,
          "description": null,
          "example": null,
          "nullable": true,
          "optional": true,
          "type": "string",
          "format": null,
          "max": null,
          "min": null
        },
        "price": {
          "default": null,
          "deprecated": false,
          "description": null,
          "example": null,
          "nullable": true,
          "optional": true,
          "type": "decimal",
          "max": null,
          "min": null
        },
        "quantity": {
          "default": null,
          "deprecated": false,
          "description": null,
          "example": null,
          "nullable": true,
          "optional": true,
          "type": "integer",
          "format": null,
          "max": null,
          "min": null
        }
      },
      "type": "object",
      "variants": []
    },
    "line_nested_create_payload": {
      "deprecated": false,
      "description": null,
      "discriminator": null,
      "example": null,
      "extends": [],
      "shape": {
        "OP": {
          "default": null,
          "deprecated": false,
          "description": null,
          "example": null,
          "nullable": false,
          "optional": true,
          "type": "literal",
          "value": "create"
        },
        "description": {
          "default": null,
          "deprecated": false,
          "description": null,
          "example": null,
          "nullable": true,
          "optional": true,
          "type": "string",
          "format": null,
          "max": null,
          "min": null
        },
        "price": {
          "default": null,
          "deprecated": false,
          "description": null,
          "example": null,
          "nullable": true,
          "optional": true,
          "type": "decimal",
          "max": null,
          "min": null
        },
        "quantity": {
          "default": null,
          "deprecated": false,
          "description": null,
          "example": null,
          "nullable": true,
          "optional": true,
          "type": "integer",
          "format": null,
          "max": null,
          "min": null
        }
      },
      "type": "object",
      "variants": []
    },
    "line_nested_delete_payload": {
      "deprecated": false,
      "description": null,
      "discriminator": null,
      "example": null,
      "extends": [],
      "shape": {
        "OP": {
          "default": null,
          "deprecated": false,
          "description": null,
          "example": null,
          "nullable": false,
          "optional": true,
          "type": "literal",
          "value": "delete"
        },
        "id": {
          "default": null,
          "deprecated": false,
          "description": null,
          "example": null,
          "nullable": false,
          "optional": false,
          "type": "string",
          "format": null,
          "max": null,
          "min": null
        }
      },
      "type": "object",
      "variants": []
    },
    "line_nested_payload": {
      "deprecated": false,
      "description": null,
      "discriminator": "OP",
      "example": null,
      "extends": [],
      "shape": {},
      "type": "union",
      "variants": [
        {
          "default": null,
          "deprecated": false,
          "description": null,
          "example": null,
          "nullable": false,
          "optional": false,
          "type": "reference",
          "reference": "line_nested_create_payload"
        },
        {
          "default": null,
          "deprecated": false,
          "description": null,
          "example": null,
          "nullable": false,
          "optional": false,
          "type": "reference",
          "reference": "line_nested_update_payload"
        },
        {
          "default": null,
          "deprecated": false,
          "description": null,
          "example": null,
          "nullable": false,
          "optional": false,
          "type": "reference",
          "reference": "line_nested_delete_payload"
        }
      ]
    },
    "line_nested_update_payload": {
      "deprecated": false,
      "description": null,
      "discriminator": null,
      "example": null,
      "extends": [],
      "shape": {
        "OP": {
          "default": null,
          "deprecated": false,
          "description": null,
          "example": null,
          "nullable": false,
          "optional": true,
          "type": "literal",
          "value": "update"
        },
        "description": {
          "default": null,
          "deprecated": false,
          "description": null,
          "example": null,
          "nullable": true,
          "optional": true,
          "type": "string",
          "format": null,
          "max": null,
          "min": null
        },
        "id": {
          "default": null,
          "deprecated": false,
          "description": null,
          "example": null,
          "nullable": false,
          "optional": true,
          "type": "string",
          "format": null,
          "max": null,
          "min": null
        },
        "price": {
          "default": null,
          "deprecated": false,
          "description": null,
          "example": null,
          "nullable": true,
          "optional": true,
          "type": "decimal",
          "max": null,
          "min": null
        },
        "quantity": {
          "default": null,
          "deprecated": false,
          "description": null,
          "example": null,
          "nullable": true,
          "optional": true,
          "type": "integer",
          "format": null,
          "max": null,
          "min": null
        }
      },
      "type": "object",
      "variants": []
    },
    "line_update_payload": {
      "deprecated": false,
      "description": null,
      "discriminator": null,
      "example": null,
      "extends": [],
      "shape": {
        "description": {
          "default": null,
          "deprecated": false,
          "description": null,
          "example": null,
          "nullable": true,
          "optional": true,
          "type": "string",
          "format": null,
          "max": null,
          "min": null
        },
        "price": {
          "default": null,
          "deprecated": false,
          "description": null,
          "example": null,
          "nullable": true,
          "optional": true,
          "type": "decimal",
          "max": null,
          "min": null
        },
        "quantity": {
          "default": null,
          "deprecated": false,
          "description": null,
          "example": null,
          "nullable": true,
          "optional": true,
          "type": "integer",
          "format": null,
          "max": null,
          "min": null
        }
      },
      "type": "object",
      "variants": []
    },
    "nullable_string_filter": {
      "deprecated": false,
      "description": null,
      "discriminator": null,
      "example": null,
      "extends": [],
      "shape": {
        "contains": {
          "default": null,
          "deprecated": false,
          "description": null,
          "example": null,
          "nullable": false,
          "optional": true,
          "type": "string",
          "format": null,
          "max": null,
          "min": null
        },
        "ends_with": {
          "default": null,
          "deprecated": false,
          "description": null,
          "example": null,
          "nullable": false,
          "optional": true,
          "type": "string",
          "format": null,
          "max": null,
          "min": null
        },
        "eq": {
          "default": null,
          "deprecated": false,
          "description": null,
          "example": null,
          "nullable": false,
          "optional": true,
          "type": "string",
          "format": null,
          "max": null,
          "min": null
        },
        "in": {
          "default": null,
          "deprecated": false,
          "description": null,
          "example": null,
          "nullable": false,
          "optional": true,
          "type": "array",
          "max": null,
          "min": null,
          "of": {
            "default": null,
            "deprecated": null,
            "description": null,
            "example": null,
            "nullable": null,
            "optional": null,
            "type": "string",
            "format": null,
            "max": null,
            "min": null
          },
          "shape": {}
        },
        "null": {
          "default": null,
          "deprecated": false,
          "description": null,
          "example": null,
          "nullable": false,
          "optional": true,
          "type": "boolean"
        },
        "starts_with": {
          "default": null,
          "deprecated": false,
          "description": null,
          "example": null,
          "nullable": false,
          "optional": true,
          "type": "string",
          "format": null,
          "max": null,
          "min": null
        }
      },
      "type": "object",
      "variants": []
    },
    "offset_pagination": {
      "deprecated": false,
      "description": null,
      "discriminator": null,
      "example": null,
      "extends": [],
      "shape": {
        "current": {
          "default": null,
          "deprecated": false,
          "description": null,
          "example": null,
          "nullable": false,
          "optional": false,
          "type": "integer",
          "format": null,
          "max": null,
          "min": null
        },
        "items": {
          "default": null,
          "deprecated": false,
          "description": null,
          "example": null,
          "nullable": false,
          "optional": false,
          "type": "integer",
          "format": null,
          "max": null,
          "min": null
        },
        "next": {
          "default": null,
          "deprecated": false,
          "description": null,
          "example": null,
          "nullable": true,
          "optional": true,
          "type": "integer",
          "format": null,
          "max": null,
          "min": null
        },
        "prev": {
          "default": null,
          "deprecated": false,
          "description": null,
          "example": null,
          "nullable": true,
          "optional": true,
          "type": "integer",
          "format": null,
          "max": null,
          "min": null
        },
        "total": {
          "default": null,
          "deprecated": false,
          "description": null,
          "example": null,
          "nullable": false,
          "optional": false,
          "type": "integer",
          "format": null,
          "max": null,
          "min": null
        }
      },
      "type": "object",
      "variants": []
    },
    "string_filter": {
      "deprecated": false,
      "description": null,
      "discriminator": null,
      "example": null,
      "extends": [],
      "shape": {
        "contains": {
          "default": null,
          "deprecated": false,
          "description": null,
          "example": null,
          "nullable": false,
          "optional": true,
          "type": "string",
          "format": null,
          "max": null,
          "min": null
        },
        "ends_with": {
          "default": null,
          "deprecated": false,
          "description": null,
          "example": null,
          "nullable": false,
          "optional": true,
          "type": "string",
          "format": null,
          "max": null,
          "min": null
        },
        "eq": {
          "default": null,
          "deprecated": false,
          "description": null,
          "example": null,
          "nullable": false,
          "optional": true,
          "type": "string",
          "format": null,
          "max": null,
          "min": null
        },
        "in": {
          "default": null,
          "deprecated": false,
          "description": null,
          "example": null,
          "nullable": false,
          "optional": true,
          "type": "array",
          "max": null,
          "min": null,
          "of": {
            "default": null,
            "deprecated": null,
            "description": null,
            "example": null,
            "nullable": null,
            "optional": null,
            "type": "string",
            "format": null,
            "max": null,
            "min": null
          },
          "shape": {}
        },
        "starts_with": {
          "default": null,
          "deprecated": false,
          "description": null,
          "example": null,
          "nullable": false,
          "optional": true,
          "type": "string",
          "format": null,
          "max": null,
          "min": null
        }
      },
      "type": "object",
      "variants": []
    }
  }
}