{
  "path": "/happy-zebra",
  "info": {},
  "types": {
    "status_filter": {
      "type": "union",
      "required": false,
      "nullable": false,
      "variants": [
        {
          "type": "status",
          "of": null,
          "partial": false
        },
        {
          "type": "object",
          "of": null,
          "partial": true,
          "shape": {
            "eq": {
              "type": "status",
              "required": false,
              "nullable": false,
              "description": null,
              "example": null,
              "format": null,
              "deprecated": false,
              "min": null,
              "max": null
            },
            "in": {
              "type": "array",
              "required": false,
              "nullable": false,
              "description": null,
              "example": null,
              "format": null,
              "deprecated": false,
              "min": null,
              "max": null,
              "of": "status"
            }
          }
        }
      ],
      "description": null,
      "example": null,
      "format": null,
      "deprecated": false
    }
  },
  "enums": {
    "status": {
      "values": [
        "draft",
        "published",
        "archived"
      ],
      "description": null,
      "example": null,
      "deprecated": false
    }
  },
  "resources": {},
  "error_codes": []
}