{
  "request": {
    "method": "GET",
    "path": "/gentle-owl/comments?filter[commentable_type][eq]=GentleOwl::Post"
  },
  "response": {
    "status": 200,
    "body": {
      "comments": [
        {
          "id": "a211fe5b-a30f-4c0a-959c-5d335f405ae1",
          "body": "Post comment",
          "authorName": "User 1",
          "commentableType": "GentleOwl::Post",
          "commentableId": "933584c2-690e-4d8e-9b30-f01666f7c44b",
          "createdAt": "2025-12-07T13:22:39.983Z"
        }
      ],
      "pagination": {
        "current": 1,
        "next": null,
        "prev": null,
        "total": 1,
        "items": 1
      }
    }
  }
}