{
  "request": {
    "method": "GET",
    "path": "/gentle-owl/comments?filter[commentable_type][eq]=GentleOwl::Post"
  },
  "response": {
    "status": 200,
    "body": {
      "comments": [
        {
          "id": "5a8049b8-fd7b-4387-a85b-6f59fc3b9956",
          "body": "Post comment",
          "author_name": "User 1",
          "commentable_type": "GentleOwl::Post",
          "commentable_id": "120421e9-eb9d-4dd3-8df9-961ac1e04868",
          "created_at": "2025-12-07T12:02:58.044Z"
        }
      ],
      "pagination": {
        "current": 1,
        "next": null,
        "prev": null,
        "total": 1,
        "items": 1
      }
    }
  }
}